cgc/__init__.py
cgc/cgc.py
cgc-1.5.0.data/scripts/cgc-cli.py
cgc-1.5.0.dist-info/LICENSE
cgc-1.5.0.dist-info/METADATA
cgc-1.5.0.dist-info/WHEEL
cgc-1.5.0.dist-info/top_level.txt
cgc-1.5.0.dist-info/RECORD
